{
	"sn": "facebook",
	"custom": {},
	"lastEventDate": "19.02.2023 15:30 1 день",
	"status": 2,
	"id": "100090009726048",
	"name": "",
	"amountFriends": "",
	"screenname": "Рогніда Прохорова",
	"birthdate": "1995 January 7",
	"country": "",
	"isAvatarExists": false,
	"cookie": [
		{
			"domain": ".facebook.com",
			"expirationDate": 1709605138,
			"hostOnly": false,
			"httpOnly": false,
			"name": "datr",
			"path": "/",
			"sameSite": "no_restriction",
			"secure": true,
			"session": false,
			"storeId": "0",
			"value": "CinXY_FyxCJXSuJy09ncEcA2"
		},
		{
			"domain": ".facebook.com",
			"expirationDate": 1756269164,
			"hostOnly": false,
			"httpOnly": false,
			"name": "locale",
			"path": "/",
			"sameSite": "no_restriction",
			"secure": true,
			"session": false,
			"storeId": "0",
			"value": "uk_UA"
		},
		{
			"domain": ".facebook.com",
			"expirationDate": 1709636387,
			"hostOnly": false,
			"httpOnly": false,
			"name": "sb",
			"path": "/",
			"sameSite": "no_restriction",
			"secure": true,
			"session": false,
			"storeId": "0",
			"value": "CinXYwTgS4qjrF2dQeXqOv4X"
		},
		{
			"domain": ".facebook.com",
			"expirationDate": 1756269164,
			"hostOnly": false,
			"httpOnly": false,
			"name": "usida",
			"path": "/",
			"sameSite": "no_restriction",
			"secure": true,
			"session": false,
			"storeId": "0",
			"value": "eyJ2ZXIiOjEsImlkIjoiQXJwZDQxNjFnaDIxeGsiLCJ0aW1lIjoxNjc1MTg4OTA2fQ%3D%3D"
		},
		{
			"domain": ".facebook.com",
			"expirationDate": 1708355276.489953,
			"hostOnly": false,
			"httpOnly": false,
			"name": "c_user",
			"path": "/",
			"sameSite": "no_restriction",
			"secure": true,
			"session": false,
			"storeId": "0",
			"value": "100090009726048"
		},
		{
			"domain": ".facebook.com",
			"expirationDate": 1677424083,
			"hostOnly": false,
			"httpOnly": false,
			"name": "dpr",
			"path": "/",
			"sameSite": "no_restriction",
			"secure": true,
			"session": false,
			"storeId": "0",
			"value": "1"
		},
		{
			"domain": ".facebook.com",
			"expirationDate": 1708355276.490033,
			"hostOnly": false,
			"httpOnly": true,
			"name": "xs",
			"path": "/",
			"sameSite": "no_restriction",
			"secure": true,
			"session": false,
			"storeId": "0",
			"value": "49%3AOja6o2UxncnOwQ%3A2%3A1675076384%3A-1%3A-1%3A%3AAcVJ_xubwEInVqt3El0O-JUOEwGmKOpIPHFmalsCkQ"
		},
		{
			"domain": ".facebook.com",
			"expirationDate": 1684595282.894181,
			"hostOnly": false,
			"httpOnly": true,
			"name": "fr",
			"path": "/",
			"sameSite": "no_restriction",
			"secure": true,
			"session": false,
			"storeId": "0",
			"value": "0ZuLm5BMxCcaFYyEn.AWWiv_W_sKvvZAk0sNQCd2Ku8fs.Bj8jtN.7y.AAA.0.0.Bj8jtU.AWV3F-fJ-sU"
		},
		{
			"domain": ".facebook.com",
			"expirationDate": 1677424265,
			"hostOnly": false,
			"httpOnly": false,
			"name": "wd",
			"path": "/",
			"sameSite": "lax",
			"secure": true,
			"session": false,
			"storeId": "0",
			"value": "775x598"
		},
		{
			"domain": ".facebook.com",
			"hostOnly": false,
			"httpOnly": false,
			"name": "presence",
			"path": "/",
			"sameSite": "unspecified",
			"secure": true,
			"session": true,
			"storeId": "0",
			"value": "C%7B%22t3%22%3A%5B%5D%2C%22utc3%22%3A1676819420581%2C%22v%22%3A1%7D"
		}
	]
}