{
	"sn": "facebook",
	"custom": {},
	"lastEventDate": "15.02.2023 13:55 3 день",
	"status": 2,
	"id": "100089672839998",
	"name": "",
	"amountFriends": "",
	"screenname": "Хриса Черкашина",
	"birthdate": "1983 January 21",
	"country": "",
	"isAvatarExists": false,
	"cookie": [
		{
			"domain": ".facebook.com",
			"expirationDate": 1709611977,
			"hostOnly": false,
			"httpOnly": false,
			"name": "datr",
			"path": "/",
			"sameSite": "no_restriction",
			"secure": true,
			"session": false,
			"storeId": "0",
			"value": "u0PXYyU5qdG_APtR-SVMJPuq"
		},
		{
			"domain": ".facebook.com",
			"expirationDate": 1756269164,
			"hostOnly": false,
			"httpOnly": false,
			"name": "locale",
			"path": "/",
			"sameSite": "no_restriction",
			"secure": true,
			"session": false,
			"storeId": "0",
			"value": "en_US"
		},
		{
			"domain": ".facebook.com",
			"expirationDate": 1709639479,
			"hostOnly": false,
			"httpOnly": false,
			"name": "sb",
			"path": "/",
			"sameSite": "no_restriction",
			"secure": true,
			"session": false,
			"storeId": "0",
			"value": "u0PXY0kLYBbeoXAbWveh1M-T"
		},
		{
			"domain": ".facebook.com",
			"expirationDate": 1756269164,
			"hostOnly": false,
			"httpOnly": false,
			"name": "usida",
			"path": "/",
			"sameSite": "no_restriction",
			"secure": true,
			"session": false,
			"storeId": "0",
			"value": "eyJ2ZXIiOjEsImlkIjoiQXJwZDc0NzExMjRiaDMiLCJ0aW1lIjoxNjc1MTkyOTAzfQ%3D%3D"
		},
		{
			"domain": ".facebook.com",
			"expirationDate": 1708004973.918448,
			"hostOnly": false,
			"httpOnly": false,
			"name": "c_user",
			"path": "/",
			"sameSite": "no_restriction",
			"secure": true,
			"session": false,
			"storeId": "0",
			"value": "100089672839998"
		},
		{
			"domain": ".facebook.com",
			"expirationDate": 1677073970,
			"hostOnly": false,
			"httpOnly": false,
			"name": "dpr",
			"path": "/",
			"sameSite": "no_restriction",
			"secure": true,
			"session": false,
			"storeId": "0",
			"value": "1.1979166269302368"
		},
		{
			"domain": ".facebook.com",
			"expirationDate": 1708004973.91851,
			"hostOnly": false,
			"httpOnly": true,
			"name": "xs",
			"path": "/",
			"sameSite": "no_restriction",
			"secure": true,
			"session": false,
			"storeId": "0",
			"value": "18%3AET4g9Jo_7kVJAA%3A2%3A1675079476%3A-1%3A-1%3A%3AAcUQ2W1ev3ifspbCWzAjs4uPDfZpamP-ha3KBwArLQ"
		},
		{
			"domain": ".facebook.com",
			"expirationDate": 1684244996.539376,
			"hostOnly": false,
			"httpOnly": true,
			"name": "fr",
			"path": "/",
			"sameSite": "no_restriction",
			"secure": true,
			"session": false,
			"storeId": "0",
			"value": "06vW9NnsDo75Ra0Yf.AWV-q4w4PNBrDUII51VSJboFEr4.Bj7OLw.yE.AAA.0.0.Bj7OMG.AWXWFedJ96I"
		},
		{
			"domain": ".facebook.com",
			"expirationDate": 1677073970,
			"hostOnly": false,
			"httpOnly": false,
			"name": "wd",
			"path": "/",
			"sameSite": "lax",
			"secure": true,
			"session": false,
			"storeId": "0",
			"value": "773x679"
		},
		{
			"domain": ".facebook.com",
			"hostOnly": false,
			"httpOnly": false,
			"name": "presence",
			"path": "/",
			"sameSite": "unspecified",
			"secure": true,
			"session": true,
			"storeId": "0",
			"value": "C%7B%22t3%22%3A%5B%5D%2C%22utc3%22%3A1676469127535%2C%22v%22%3A1%7D"
		}
	]
}